nvim_mgr/__init__.py
nvim_mgr/__main__.py
nvim_mgr-0.1.3.dist-info/METADATA
nvim_mgr-0.1.3.dist-info/WHEEL
nvim_mgr-0.1.3.dist-info/entry_points.txt
nvim_mgr-0.1.3.dist-info/RECORD
