Metadata-Version: 2.1
Name: nvim-mgr
Version: 0.1.3
Summary: Manage Multiple Nvim instances.
Author: Evan Voyles
Author-email: evan.voyles@intrafentech.com
Requires-Python: >=3.11,<4.0
Classifier: Programming Language :: Python :: 3
Classifier: Programming Language :: Python :: 3.11
Classifier: Programming Language :: Python :: 3.12
Requires-Dist: fastapi[uvicorn] (>=0.112.1,<0.113.0)
Requires-Dist: typer (>=0.12.4,<0.13.0)
Requires-Dist: uvicorn (>=0.30.6,<0.31.0)
